<?xml version="1.0" encoding="UTF-8" standalone="no"?>
<geonames>
<geoname>
<name>Gräsalp</name>
<lat>47.3086111</lat>
<lng>10.0061111</lng>
<geonameId>2778112</geonameId>
<countryCode>AT</countryCode>
<countryName>Austria</countryName>
<fcl>P</fcl>
<fcode>PPL</fcode>
<distance>1.0626</distance>
</geoname>
<geoname>
<name>Schoppernau</name>
<lat>47.3133333</lat>
<lng>10.0175</lng>
<geonameId>2765650</geonameId>
<countryCode>AT</countryCode>
<countryName>Austria</countryName>
<fcl>P</fcl>
<fcode>PPL</fcode>
<distance>1.9846</distance>
</geoname>
<geoname>
<name>Argenau</name>
<lat>47.3194444</lat>
<lng>9.985</lng>
<geonameId>2782433</geonameId>
<countryCode>AT</countryCode>
<countryName>Austria</countryName>
<fcl>P</fcl>
<fcode>PPL</fcode>
<distance>2.4399</distance>
</geoname>
<geoname>
<name>Rehmen</name>
<lat>47.3219444</lat>
<lng>9.9975</lng>
<geonameId>3330190</geonameId>
<countryCode>AT</countryCode>
<countryName>Austria</countryName>
<fcl>P</fcl>
<fcode>PPL</fcode>
<distance>2.4473</distance>
</geoname>
<geoname>
<name>Rehmen</name>
<lat>47.3222222</lat>
<lng>9.9975</lng>
<geonameId>2767787</geonameId>
<countryCode>AT</countryCode>
<countryName>Austria</countryName>
<fcl>P</fcl>
<fcode>PPL</fcode>
<distance>2.4781</distance>
</geoname>
<geoname>
<name>Schalzbachvorsäß</name>
<lat>47.2936111</lat>
<lng>10.0375</lng>
<geonameId>2766166</geonameId>
<countryCode>AT</countryCode>
<countryName>Austria</countryName>
<fcl>P</fcl>
<fcode>PPL</fcode>
<distance>2.9157</distance>
</geoname>
<geoname>
<name>Au</name>
<lat>47.3227778</lat>
<lng>9.9758333</lng>
<geonameId>2782259</geonameId>
<countryCode>AT</countryCode>
<countryName>Austria</countryName>
<fcl>P</fcl>
<fcode>PPL</fcode>
<distance>3.1199</distance>
</geoname>
<geoname>
<name>Argenzipfel</name>
<lat>47.3183333</lat>
<lng>9.9677778</lng>
<geonameId>3330189</geonameId>
<countryCode>AT</countryCode>
<countryName>Austria</countryName>
<fcl>P</fcl>
<fcode>PPL</fcode>
<distance>3.1712</distance>
</geoname>
<geoname>
<name>Schwende</name>
<lat>47.2869444</lat>
<lng>9.9155556</lng>
<geonameId>2765358</geonameId>
<countryCode>AT</countryCode>
<countryName>Austria</countryName>
<fcl>P</fcl>
<fcode>PPL</fcode>
<distance>6.5316</distance>
</geoname>
<geoname>
<name>Schnepfau</name>
<lat>47.35</lat>
<lng>9.95</lng>
<geonameId>2765798</geonameId>
<countryCode>AT</countryCode>
<countryName>Austria</countryName>
<fcl>P</fcl>
<fcode>PPL</fcode>
<distance>6.7163</distance>
</geoname>
</geonames>